AUTHORS.rst
CHANGELOG.rst
LICENSE
MANIFEST.in
README.rst
setup.py
django_order.egg-info/PKG-INFO
django_order.egg-info/SOURCES.txt
django_order.egg-info/dependency_links.txt
django_order.egg-info/not-zip-safe
django_order.egg-info/requires.txt
django_order.egg-info/top_level.txt
order/__init__.py
order/managers.py
order/models.py
order/signal_handlers.py
order/tests.py
order/tools.py
order/utils.py
order/templates/admin/order/change_list.html